pytest_codeblock/__init__.py
pytest_codeblock/collector.py
pytest_codeblock/config.py
pytest_codeblock/constants.py
pytest_codeblock/helpers.py
pytest_codeblock/md.py
pytest_codeblock/rst.py
pytest_codeblock/tests/__init__.py
pytest_codeblock/tests/conftest.py
pytest_codeblock/tests/test_customisation.py
pytest_codeblock/tests/test_integration.py
pytest_codeblock/tests/test_pytest_codeblock.py
pytest_codeblock-0.4.dist-info/licenses/LICENSE
pytest_codeblock-0.4.dist-info/METADATA
pytest_codeblock-0.4.dist-info/WHEEL
pytest_codeblock-0.4.dist-info/entry_points.txt
pytest_codeblock-0.4.dist-info/top_level.txt
pytest_codeblock-0.4.dist-info/RECORD
