Metadata-Version: 2.4
Name: pytest-codeblock
Version: 0.4
Summary: Pytest plugin to collect and test code blocks in reStructuredText and Markdown files.
Author-email: Artur Barseghyan <artur.barseghyan@gmail.com>
Maintainer-email: Artur Barseghyan <artur.barseghyan@gmail.com>
License-Expression: MIT
Project-URL: Homepage, https://github.com/barseghyanartur/pytest-codeblock/
Project-URL: Repository, https://github.com/barseghyanartur/pytest-codeblock/
Project-URL: Issues, https://github.com/barseghyanartur/pytest-codeblock/issues
Project-URL: Documentation, https://pytest-codeblock.readthedocs.io/
Project-URL: Changelog, https://pytest-codeblock.readthedocs.io/en/latest/changelog.html
Keywords: pytest,plugin,documentation,code blocks,markdown,rst
Classifier: Framework :: Pytest
Classifier: Development Status :: 4 - Beta
Classifier: Intended Audience :: Developers
Classifier: Operating System :: OS Independent
Classifier: Programming Language :: Python :: 3.10
Classifier: Programming Language :: Python :: 3.11
Classifier: Programming Language :: Python :: 3.12
Classifier: Programming Language :: Python :: 3.13
Classifier: Programming Language :: Python :: 3.14
Classifier: Programming Language :: Python
Classifier: Topic :: Software Development :: Testing
Classifier: Topic :: Software Development
Requires-Python: >=3.10
License-File: LICENSE
Requires-Dist: pytest
Requires-Dist: tomli; python_version < "3.11"
Provides-Extra: all
Requires-Dist: pytest-codeblock[build,dev,docs,test]; extra == "all"
Provides-Extra: dev
Requires-Dist: detect-secrets; extra == "dev"
Requires-Dist: doc8; extra == "dev"
Requires-Dist: ipython; extra == "dev"
Requires-Dist: mypy; extra == "dev"
Requires-Dist: pydoclint; extra == "dev"
Requires-Dist: ruff; extra == "dev"
Requires-Dist: twine; extra == "dev"
Requires-Dist: uv; extra == "dev"
Provides-Extra: test
Requires-Dist: django; extra == "test"
Requires-Dist: fake.py; extra == "test"
Requires-Dist: moto[s3]; extra == "test"
Requires-Dist: openai; extra == "test"
Requires-Dist: pytest; extra == "test"
Requires-Dist: pytest-cov; extra == "test"
Requires-Dist: pytest-django; extra == "test"
Provides-Extra: docs
Requires-Dist: sphinx<6.0; extra == "docs"
Requires-Dist: sphinx-autobuild; extra == "docs"
Requires-Dist: sphinx-rtd-theme>=1.3.0; extra == "docs"
Requires-Dist: sphinx-no-pragma; extra == "docs"
Requires-Dist: sphinx-llms-txt-link; extra == "docs"
Provides-Extra: build
Requires-Dist: build; extra == "build"
Requires-Dist: twine; extra == "build"
Requires-Dist: wheel; extra == "build"
Dynamic: license-file
